Workbook

Sheet Итоги
A1: LawTracker — окупаемость (без затрат на разработку)
A2: Ориентировочная модель. Меняйте синие ячейки на листах «Допущения» и «Расходы»: всё остальное пересчитывается.
A4: Показатель | B4: Минимальный сценарий | C4: Реалистичный сценарий
A5: Разовые расходы на запуск, ₽ | B5: =Расходы!B11 | C5: =Расходы!C11
A6: Постоянные расходы в месяц, ₽ | B6: =Расходы!B24 | C6: =Расходы!C24
A7: Безубыточность: платных клиентов (смесь тарифов) | B7: =Безубыточность!D7 | C7: =Безубыточность!E7
A8: Платных клиентов через 12 месяцев | B8: =Прогноз_мин!D16 | C8: =Прогноз_реал!D16
A9: Платных клиентов через 24 месяца | B9: =Прогноз_мин!D28 | C9: =Прогноз_реал!D28
A10: Выручка за 24 месяца, ₽ | B10: =Прогноз_мин!F30 | C10: =Прогноз_реал!F30
A11: Прибыль за 24 месяца до учёта разовых расходов, ₽ | B11: =Прогноз_мин!J30 | C11: =Прогноз_реал!J30
A12: Накопленный денежный поток через 12 месяцев, ₽ | B12: =Прогноз_мин!K16 | C12: =Прогноз_реал!K16
A13: Накопленный денежный поток через 24 месяца, ₽ | B13: =Прогноз_мин!K28 | C13: =Прогноз_реал!K28
A14: Максимальный «провал» накопленного потока (нужное финансирование), ₽ | B14: =-MIN(Прогноз_мин!K5:K28) | C14: =-MIN(Прогноз_реал!K5:K28)
A15: Первый месяц с прибылью за месяц | B15: =IF(COUNT(Прогноз_мин!M5:M28)=0,"нет за 24 мес.",MIN(Прогноз_мин!M5:M28)) | C15: =IF(COUNT(Прогноз_реал!M5:M28)=0,"нет за 24 мес.",MIN(Прогноз_реал!M5:M28))
A16: Месяц окупаемости (накопленный итог ≥ 0) | B16: =IF(COUNT(Прогноз_мин!L5:L28)=0,"нет за 24 мес.",MIN(Прогноз_мин!L5:L28)) | C16: =IF(COUNT(Прогноз_реал!L5:L28)=0,"нет за 24 мес.",MIN(Прогноз_реал!L5:L28))
A18: Как читать
A19: • Месяцы 1–3 — разработка, пилот и тестирование без выручки (по плану презентации), продажи начинаются с месяца из листа «Допущения».
A20: • Накопленный денежный поток учитывает разовые расходы в 1-м месяце. Разработка сайта и серверов под нагрузку не включены.
A21: • Цены тарифов предварительные и не утверждены; корпоративный тариф («по запросу») в выручку не включён.
A22: • Проверяйте допущения: особенно приток клиентов, отток, цену и стоимость ИИ на клиента — они сильнее всего влияют на результат.

Sheet Допущения
A1: LawTracker — допущения модели окупаемости
A2: Синий шрифт — входные данные (можно менять). Жёлтая заливка — ключевые допущения. Все суммы в рублях. Значения — мои оценки для планирования, а не данные рынка или утверждённые тарифы.
A4: Параметр | B4: Значение | C4: Комментарий / источник
A5: ВЫРУЧКА
A6: Цена тарифа «Базовый», ₽/мес | B6: 690 | C6: Рекомендованная цена с сайта (раздел «Тарифы»); ориентир — конкурент от ~3 500 ₽/мес; не утверждена
A7: Цена тарифа «Профессиональный», ₽/мес | B7: 1690 | C7: Рекомендованная цена с сайта; не утверждена
A8: Доля платных клиентов на «Базовом» | B8: 0.6 | C8: Допущение: большинство — ИП и микробизнес
A9: Доля платных клиентов на «Профессиональном» | B9: =1-B8 | C9: Считается: 100 % минус доля «Базового»
A10: Средний чек (ARPU), ₽/мес на платного клиента | B10: =B6*B8+B7*B9 | C10: Считается. Корпоративный тариф («по запросу») не учтён
A11: Бесплатных пользователей на 1 платного | B11: 3 | C11: Допущение: бесплатный старт создаёт нагрузку (ИИ, хостинг)
A12: Комиссия эквайринга, % от выручки | B12: 0.03 | C12: Допущение: 2–3,5 % обычно
A13: Налог (УСН «доходы»), % от выручки | B13: 0.06 | C13: Допущение: УСН 6 %; возможны льготы, уточнить у бухгалтера
A14: Отток платных клиентов, % в месяц | B14: 0.04 | C14: Допущение
A15: РОСТ ПРОДАЖ
A16: Месяц начала продаж | B16: 4 | C16: По плану презентации: 3 месяца — исследование, прототип, тест; продажи с 4-го
A17: Новых платных клиентов в первый месяц продаж | B17: 10 | C17: Допущение (пилоты, партнёры-бухгалтеры)
A18: Рост притока новых клиентов, % в месяц | B18: 0.1 | C18: Допущение
A19: Потолок притока новых клиентов, чел. в месяц | B19: 100 | C19: Допущение: ограничение маркетингового бюджета
A20: ПЕРЕМЕННЫЕ РАСХОДЫ
A21: ИИ и хостинг на 1 пользователя (платного и бесплатного), ₽/мес | B21: 60 | C21: Допущение; уточнить по итогам пилота
A22: Страховые взносы с зарплат, % | B22: 0.3 | C22: Допущение: ~30 %; для IT-компаний возможны льготы

Sheet Расходы
A1: Расходы без разработки, ₽
A2: Две колонки сценариев: «Минимальный» — бета-версия: ежемесячно только хостинг и рассылки, ИИ на бесплатных токенах GigaChat, основатели без зарплат, юрист и бухгалтер без оплаты; «Реалистичный» — небольшая команда без разработчиков (не менялся). «Облагается взносами» = 1, если это зарплата штатного сотрудника. Пояснения к ячейкам минимального сценария — в комментариях.
A4: РАЗОВЫЕ РАСХОДЫ НА ЗАПУСК | B4: Минимальный | C4: Реалистичный | D4: Комментарий
A5: Регистрация юрлица или ИП, банк, бухгалтерский старт | B5: 10000 | C5: 20000
A6: Юридические документы (политика, соглашение, согласие на обработку данных) | B6: 40000 | C6: 100000
A7: Товарный знак (пошлины и патентный поверенный) | B7: 30000 | C7: 60000
A8: Брендинг (логотип, фирменный стиль) | B8: 10000 | C8: 60000
A9: Проверка безопасности (пентест) перед продажами | B9: 0 | C9: 100000
A10: Домен, сертификаты, прочее | B10: 10000 | C10: 10000
A11: Итого разовые | B11: =SUM(B5:B10) | C11: =SUM(C5:C10)
A13: ЕЖЕМЕСЯЧНЫЕ РАСХОДЫ | B13: Минимальный | C13: Реалистичный | D13: Облагается взносами (мин.) | E13: Облагается взносами (реал.)
A14: Хостинг и облако в РФ | B14: 300 | C14: 30000 | D14: 0 | E14: 0
A15: ИИ-анализ изменений (базовая часть) | B15: 0 | C15: 40000 | D15: 0 | E15: 0
A16: Сервисы: рассылки, почта, аналитика, CRM, поддержка | B16: 770 | C16: 15000 | D16: 0 | E16: 0
A17: Юрист-эксперт | B17: 0 | C17: 90000 | D17: 0 | E17: 1
A18: Маркетолог и контент | B18: 0 | C18: 70000 | D18: 0 | E18: 1
A19: Основатель или продукт-менеджер | B19: 0 | C19: 120000 | D19: 0 | E19: 1
A20: Поддержка клиентов | B20: 0 | C20: 30000 | D20: 0 | E20: 1
A21: Бухгалтер на аутсорсе | B21: 0 | C21: 10000 | D21: 0 | E21: 0
A22: Рекламный бюджет и партнёры | B22: 0 | C22: 100000 | D22: 0 | E22: 0
A23: Страховые взносы с зарплат | B23: =Допущения!$B$22*SUMPRODUCT(B14:B22,D14:D22) | C23: =Допущения!$B$22*SUMPRODUCT(C14:C22,E14:E22)
A24: Итого постоянные расходы в месяц | B24: =SUM(B14:B23) | C24: =SUM(C14:C23)

Sheet Прогноз_мин
A1: Прогноз: минимальный сценарий
A2: Помесячный прогноз на 24 месяца. Все параметры берутся из листов «Допущения» и «Расходы».
A4: Месяц | B4: Новые платные клиенты | C4: Отток | D4: Платные клиенты (конец) | E4: Бесплатные пользователи | F4: Выручка, ₽ | G4: Переменные расходы, ₽ | H4: Постоянные расходы, ₽ | I4: Эквайринг и налог, ₽ | J4: Прибыль за месяц, ₽ | K4: Накопленный денежный поток, ₽ | L4: Вехи: накопленный итог ≥ 0 | M4: Вехи: прибыль за месяц > 0
A5: 1 | B5: =IF(A5<Допущения!$B$16,0,MIN(Допущения!$B$19,ROUND(Допущения!$B$17*(1+Допущения!$B$18)^(A5-Допущения!$B$16),0))) | C5: =0 | D5: =B5-C5 | E5: =D5*Допущения!$B$11 | F5: =D5*Допущения!$B$10 | G5: =(D5+E5)*Допущения!$B$21 | H5: =Расходы!$B$24 | I5: =F5*(Допущения!$B$12+Допущения!$B$13) | J5: =F5-G5-H5-I5 | K5: =-Расходы!$B$11+J5 | L5: =IF(K5>=0,A5,"") | M5: =IF(J5>0,A5,"")
A6: 2 | B6: =IF(A6<Допущения!$B$16,0,MIN(Допущения!$B$19,ROUND(Допущения!$B$17*(1+Допущения!$B$18)^(A6-Допущения!$B$16),0))) | C6: =ROUND(D5*Допущения!$B$14,0) | D6: =D5+B6-C6 | E6: =D6*Допущения!$B$11 | F6: =D6*Допущения!$B$10 | G6: =(D6+E6)*Допущения!$B$21 | H6: =Расходы!$B$24 | I6: =F6*(Допущения!$B$12+Допущения!$B$13) | J6: =F6-G6-H6-I6 | K6: =K5+J6 | L6: =IF(K6>=0,A6,"") | M6: =IF(J6>0,A6,"")
A7: 3 | B7: =IF(A7<Допущения!$B$16,0,MIN(Допущения!$B$19,ROUND(Допущения!$B$17*(1+Допущения!$B$18)^(A7-Допущения!$B$16),0))) | C7: =ROUND(D6*Допущения!$B$14,0) | D7: =D6+B7-C7 | E7: =D7*Допущения!$B$11 | F7: =D7*Допущения!$B$10 | G7: =(D7+E7)*Допущения!$B$21 | H7: =Расходы!$B$24 | I7: =F7*(Допущения!$B$12+Допущения!$B$13) | J7: =F7-G7-H7-I7 | K7: =K6+J7 | L7: =IF(K7>=0,A7,"") | M7: =IF(J7>0,A7,"")
A8: 4 | B8: =IF(A8<Допущения!$B$16,0,MIN(Допущения!$B$19,ROUND(Допущения!$B$17*(1+Допущения!$B$18)^(A8-Допущения!$B$16),0))) | C8: =ROUND(D7*Допущения!$B$14,0) | D8: =D7+B8-C8 | E8: =D8*Допущения!$B$11 | F8: =D8*Допущения!$B$10 | G8: =(D8+E8)*Допущения!$B$21 | H8: =Расходы!$B$24 | I8: =F8*(Допущения!$B$12+Допущения!$B$13) | J8: =F8-G8-H8-I8 | K8: =K7+J8 | L8: =IF(K8>=0,A8,"") | M8: =IF(J8>0,A8,"")
A9: 5 | B9: =IF(A9<Допущения!$B$16,0,MIN(Допущения!$B$19,ROUND(Допущения!$B$17*(1+Допущения!$B$18)^(A9-Допущения!$B$16),0))) | C9: =ROUND(D8*Допущения!$B$14,0) | D9: =D8+B9-C9 | E9: =D9*Допущения!$B$11 | F9: =D9*Допущения!$B$10 | G9: =(D9+E9)*Допущения!$B$21 | H9: =Расходы!$B$24 | I9: =F9*(Допущения!$B$12+Допущения!$B$13) | J9: =F9-G9-H9-I9 | K9: =K8+J9 | L9: =IF(K9>=0,A9,"") | M9: =IF(J9>0,A9,"")
A10: 6 | B10: =IF(A10<Допущения!$B$16,0,MIN(Допущения!$B$19,ROUND(Допущения!$B$17*(1+Допущения!$B$18)^(A10-Допущения!$B$16),0))) | C10: =ROUND(D9*Допущения!$B$14,0) | D10: =D9+B10-C10 | E10: =D10*Допущения!$B$11 | F10: =D10*Допущения!$B$10 | G10: =(D10+E10)*Допущения!$B$21 | H10: =Расходы!$B$24 | I10: =F10*(Допущения!$B$12+Допущения!$B$13) | J10: =F10-G10-H10-I10 | K10: =K9+J10 | L10: =IF(K10>=0,A10,"") | M10: =IF(J10>0,A10,"")
A11: 7 | B11: =IF(A11<Допущения!$B$16,0,MIN(Допущения!$B$19,ROUND(Допущения!$B$17*(1+Допущения!$B$18)^(A11-Допущения!$B$16),0))) | C11: =ROUND(D10*Допущения!$B$14,0) | D11: =D10+B11-C11 | E11: =D11*Допущения!$B$11 | F11: =D11*Допущения!$B$10 | G11: =(D11+E11)*Допущения!$B$21 | H11: =Расходы!$B$24 | I11: =F11*(Допущения!$B$12+Допущения!$B$13) | J11: =F11-G11-H11-I11 | K11: =K10+J11 | L11: =IF(K11>=0,A11,"") | M11: =IF(J11>0,A11,"")
A12: 8 | B12: =IF(A12<Допущения!$B$16,0,MIN(Допущения!$B$19,ROUND(Допущения!$B$17*(1+Допущения!$B$18)^(A12-Допущения!$B$16),0))) | C12: =ROUND(D11*Допущения!$B$14,0) | D12: =D11+B12-C12 | E12: =D12*Допущения!$B$11 | F12: =D12*Допущения!$B$10 | G12: =(D12+E12)*Допущения!$B$21 | H12: =Расходы!$B$24 | I12: =F12*(Допущения!$B$12+Допущения!$B$13) | J12: =F12-G12-H12-I12 | K12: =K11+J12 | L12: =IF(K12>=0,A12,"") | M12: =IF(J12>0,A12,"")
A13: 9 | B13: =IF(A13<Допущения!$B$16,0,MIN(Допущения!$B$19,ROUND(Допущения!$B$17*(1+Допущения!$B$18)^(A13-Допущения!$B$16),0))) | C13: =ROUND(D12*Допущения!$B$14,0) | D13: =D12+B13-C13 | E13: =D13*Допущения!$B$11 | F13: =D13*Допущения!$B$10 | G13: =(D13+E13)*Допущения!$B$21 | H13: =Расходы!$B$24 | I13: =F13*(Допущения!$B$12+Допущения!$B$13) | J13: =F13-G13-H13-I13 | K13: =K12+J13 | L13: =IF(K13>=0,A13,"") | M13: =IF(J13>0,A13,"")
A14: 10 | B14: =IF(A14<Допущения!$B$16,0,MIN(Допущения!$B$19,ROUND(Допущения!$B$17*(1+Допущения!$B$18)^(A14-Допущения!$B$16),0))) | C14: =ROUND(D13*Допущения!$B$14,0) | D14: =D13+B14-C14 | E14: =D14*Допущения!$B$11 | F14: =D14*Допущения!$B$10 | G14: =(D14+E14)*Допущения!$B$21 | H14: =Расходы!$B$24 | I14: =F14*(Допущения!$B$12+Допущения!$B$13) | J14: =F14-G14-H14-I14 | K14: =K13+J14 | L14: =IF(K14>=0,A14,"") | M14: =IF(J14>0,A14,"")
A15: 11 | B15: =IF(A15<Допущения!$B$16,0,MIN(Допущения!$B$19,ROUND(Допущения!$B$17*(1+Допущения!$B$18)^(A15-Допущения!$B$16),0))) | C15: =ROUND(D14*Допущения!$B$14,0) | D15: =D14+B15-C15 | E15: =D15*Допущения!$B$11 | F15: =D15*Допущения!$B$10 | G15: =(D15+E15)*Допущения!$B$21 | H15: =Расходы!$B$24 | I15: =F15*(Допущения!$B$12+Допущения!$B$13) | J15: =F15-G15-H15-I15 | K15: =K14+J15 | L15: =IF(K15>=0,A15,"") | M15: =IF(J15>0,A15,"")
A16: 12 | B16: =IF(A16<Допущения!$B$16,0,MIN(Допущения!$B$19,ROUND(Допущения!$B$17*(1+Допущения!$B$18)^(A16-Допущения!$B$16),0))) | C16: =ROUND(D15*Допущения!$B$14,0) | D16: =D15+B16-C16 | E16: =D16*Допущения!$B$11 | F16: =D16*Допущения!$B$10 | G16: =(D16+E16)*Допущения!$B$21 | H16: =Расходы!$B$24 | I16: =F16*(Допущения!$B$12+Допущения!$B$13) | J16: =F16-G16-H16-I16 | K16: =K15+J16 | L16: =IF(K16>=0,A16,"") | M16: =IF(J16>0,A16,"")
A17: 13 | B17: =IF(A17<Допущения!$B$16,0,MIN(Допущения!$B$19,ROUND(Допущения!$B$17*(1+Допущения!$B$18)^(A17-Допущения!$B$16),0))) | C17: =ROUND(D16*Допущения!$B$14,0) | D17: =D16+B17-C17 | E17: =D17*Допущения!$B$11 | F17: =D17*Допущения!$B$10 | G17: =(D17+E17)*Допущения!$B$21 | H17: =Расходы!$B$24 | I17: =F17*(Допущения!$B$12+Допущения!$B$13) | J17: =F17-G17-H17-I17 | K17: =K16+J17 | L17: =IF(K17>=0,A17,"") | M17: =IF(J17>0,A17,"")
... A28: 24 | B28: =IF(A28<Допущения!$B$16,0,MIN(Допущения!$B$19,ROUND(Допущения!$B$17*(1+Допущения!$B$18)^(A28-Допущения!$B$16),0))) | C28: =ROUND(D27*Допущения!$B$14,0) | D28: =D27+B28-C28 | E28: =D28*Допущения!$B$11 | F28: =D28*Допущения!$B$10 | G28: =(D28+E28)*Допущения!$B$21 | H28: =Расходы!$B$24 | I28: =F28*(Допущения!$B$12+Допущения!$B$13) | J28: =F28-G28-H28-I28 | K28: =K27+J28 | L28: =IF(K28>=0,A28,"") | M28: =IF(J28>0,A28,"")
A30: Итого за 24 месяца | F30: =SUM(F5:F28) | G30: =SUM(G5:G28) | H30: =SUM(H5:H28) | I30: =SUM(I5:I28) | J30: =SUM(J5:J28)
A31: Разовые расходы на запуск (учтены в накопленном итоге с 1-го месяца) | J31: =Расходы!B11

Sheet Прогноз_реал
A1: Прогноз: реалистичный сценарий
A2: Помесячный прогноз на 24 месяца. Все параметры берутся из листов «Допущения» и «Расходы».
A4: Месяц | B4: Новые платные клиенты | C4: Отток | D4: Платные клиенты (конец) | E4: Бесплатные пользователи | F4: Выручка, ₽ | G4: Переменные расходы, ₽ | H4: Постоянные расходы, ₽ | I4: Эквайринг и налог, ₽ | J4: Прибыль за месяц, ₽ | K4: Накопленный денежный поток, ₽ | L4: Вехи: накопленный итог ≥ 0 | M4: Вехи: прибыль за месяц > 0
A5: 1 | B5: =IF(A5<Допущения!$B$16,0,MIN(Допущения!$B$19,ROUND(Допущения!$B$17*(1+Допущения!$B$18)^(A5-Допущения!$B$16),0))) | C5: =0 | D5: =B5-C5 | E5: =D5*Допущения!$B$11 | F5: =D5*Допущения!$B$10 | G5: =(D5+E5)*Допущения!$B$21 | H5: =Расходы!$C$24 | I5: =F5*(Допущения!$B$12+Допущения!$B$13) | J5: =F5-G5-H5-I5 | K5: =-Расходы!$C$11+J5 | L5: =IF(K5>=0,A5,"") | M5: =IF(J5>0,A5,"")
A6: 2 | B6: =IF(A6<Допущения!$B$16,0,MIN(Допущения!$B$19,ROUND(Допущения!$B$17*(1+Допущения!$B$18)^(A6-Допущения!$B$16),0))) | C6: =ROUND(D5*Допущения!$B$14,0) | D6: =D5+B6-C6 | E6: =D6*Допущения!$B$11 | F6: =D6*Допущения!$B$10 | G6: =(D6+E6)*Допущения!$B$21 | H6: =Расходы!$C$24 | I6: =F6*(Допущения!$B$12+Допущения!$B$13) | J6: =F6-G6-H6-I6 | K6: =K5+J6 | L6: =IF(K6>=0,A6,"") | M6: =IF(J6>0,A6,"")
A7: 3 | B7: =IF(A7<Допущения!$B$16,0,MIN(Допущения!$B$19,ROUND(Допущения!$B$17*(1+Допущения!$B$18)^(A7-Допущения!$B$16),0))) | C7: =ROUND(D6*Допущения!$B$14,0) | D7: =D6+B7-C7 | E7: =D7*Допущения!$B$11 | F7: =D7*Допущения!$B$10 | G7: =(D7+E7)*Допущения!$B$21 | H7: =Расходы!$C$24 | I7: =F7*(Допущения!$B$12+Допущения!$B$13) | J7: =F7-G7-H7-I7 | K7: =K6+J7 | L7: =IF(K7>=0,A7,"") | M7: =IF(J7>0,A7,"")
A8: 4 | B8: =IF(A8<Допущения!$B$16,0,MIN(Допущения!$B$19,ROUND(Допущения!$B$17*(1+Допущения!$B$18)^(A8-Допущения!$B$16),0))) | C8: =ROUND(D7*Допущения!$B$14,0) | D8: =D7+B8-C8 | E8: =D8*Допущения!$B$11 | F8: =D8*Допущения!$B$10 | G8: =(D8+E8)*Допущения!$B$21 | H8: =Расходы!$C$24 | I8: =F8*(Допущения!$B$12+Допущения!$B$13) | J8: =F8-G8-H8-I8 | K8: =K7+J8 | L8: =IF(K8>=0,A8,"") | M8: =IF(J8>0,A8,"")
A9: 5 | B9: =IF(A9<Допущения!$B$16,0,MIN(Допущения!$B$19,ROUND(Допущения!$B$17*(1+Допущения!$B$18)^(A9-Допущения!$B$16),0))) | C9: =ROUND(D8*Допущения!$B$14,0) | D9: =D8+B9-C9 | E9: =D9*Допущения!$B$11 | F9: =D9*Допущения!$B$10 | G9: =(D9+E9)*Допущения!$B$21 | H9: =Расходы!$C$24 | I9: =F9*(Допущения!$B$12+Допущения!$B$13) | J9: =F9-G9-H9-I9 | K9: =K8+J9 | L9: =IF(K9>=0,A9,"") | M9: =IF(J9>0,A9,"")
A10: 6 | B10: =IF(A10<Допущения!$B$16,0,MIN(Допущения!$B$19,ROUND(Допущения!$B$17*(1+Допущения!$B$18)^(A10-Допущения!$B$16),0))) | C10: =ROUND(D9*Допущения!$B$14,0) | D10: =D9+B10-C10 | E10: =D10*Допущения!$B$11 | F10: =D10*Допущения!$B$10 | G10: =(D10+E10)*Допущения!$B$21 | H10: =Расходы!$C$24 | I10: =F10*(Допущения!$B$12+Допущения!$B$13) | J10: =F10-G10-H10-I10 | K10: =K9+J10 | L10: =IF(K10>=0,A10,"") | M10: =IF(J10>0,A10,"")
A11: 7 | B11: =IF(A11<Допущения!$B$16,0,MIN(Допущения!$B$19,ROUND(Допущения!$B$17*(1+Допущения!$B$18)^(A11-Допущения!$B$16),0))) | C11: =ROUND(D10*Допущения!$B$14,0) | D11: =D10+B11-C11 | E11: =D11*Допущения!$B$11 | F11: =D11*Допущения!$B$10 | G11: =(D11+E11)*Допущения!$B$21 | H11: =Расходы!$C$24 | I11: =F11*(Допущения!$B$12+Допущения!$B$13) | J11: =F11-G11-H11-I11 | K11: =K10+J11 | L11: =IF(K11>=0,A11,"") | M11: =IF(J11>0,A11,"")
A12: 8 | B12: =IF(A12<Допущения!$B$16,0,MIN(Допущения!$B$19,ROUND(Допущения!$B$17*(1+Допущения!$B$18)^(A12-Допущения!$B$16),0))) | C12: =ROUND(D11*Допущения!$B$14,0) | D12: =D11+B12-C12 | E12: =D12*Допущения!$B$11 | F12: =D12*Допущения!$B$10 | G12: =(D12+E12)*Допущения!$B$21 | H12: =Расходы!$C$24 | I12: =F12*(Допущения!$B$12+Допущения!$B$13) | J12: =F12-G12-H12-I12 | K12: =K11+J12 | L12: =IF(K12>=0,A12,"") | M12: =IF(J12>0,A12,"")
A13: 9 | B13: =IF(A13<Допущения!$B$16,0,MIN(Допущения!$B$19,ROUND(Допущения!$B$17*(1+Допущения!$B$18)^(A13-Допущения!$B$16),0))) | C13: =ROUND(D12*Допущения!$B$14,0) | D13: =D12+B13-C13 | E13: =D13*Допущения!$B$11 | F13: =D13*Допущения!$B$10 | G13: =(D13+E13)*Допущения!$B$21 | H13: =Расходы!$C$24 | I13: =F13*(Допущения!$B$12+Допущения!$B$13) | J13: =F13-G13-H13-I13 | K13: =K12+J13 | L13: =IF(K13>=0,A13,"") | M13: =IF(J13>0,A13,"")
A14: 10 | B14: =IF(A14<Допущения!$B$16,0,MIN(Допущения!$B$19,ROUND(Допущения!$B$17*(1+Допущения!$B$18)^(A14-Допущения!$B$16),0))) | C14: =ROUND(D13*Допущения!$B$14,0) | D14: =D13+B14-C14 | E14: =D14*Допущения!$B$11 | F14: =D14*Допущения!$B$10 | G14: =(D14+E14)*Допущения!$B$21 | H14: =Расходы!$C$24 | I14: =F14*(Допущения!$B$12+Допущения!$B$13) | J14: =F14-G14-H14-I14 | K14: =K13+J14 | L14: =IF(K14>=0,A14,"") | M14: =IF(J14>0,A14,"")
A15: 11 | B15: =IF(A15<Допущения!$B$16,0,MIN(Допущения!$B$19,ROUND(Допущения!$B$17*(1+Допущения!$B$18)^(A15-Допущения!$B$16),0))) | C15: =ROUND(D14*Допущения!$B$14,0) | D15: =D14+B15-C15 | E15: =D15*Допущения!$B$11 | F15: =D15*Допущения!$B$10 | G15: =(D15+E15)*Допущения!$B$21 | H15: =Расходы!$C$24 | I15: =F15*(Допущения!$B$12+Допущения!$B$13) | J15: =F15-G15-H15-I15 | K15: =K14+J15 | L15: =IF(K15>=0,A15,"") | M15: =IF(J15>0,A15,"")
A16: 12 | B16: =IF(A16<Допущения!$B$16,0,MIN(Допущения!$B$19,ROUND(Допущения!$B$17*(1+Допущения!$B$18)^(A16-Допущения!$B$16),0))) | C16: =ROUND(D15*Допущения!$B$14,0) | D16: =D15+B16-C16 | E16: =D16*Допущения!$B$11 | F16: =D16*Допущения!$B$10 | G16: =(D16+E16)*Допущения!$B$21 | H16: =Расходы!$C$24 | I16: =F16*(Допущения!$B$12+Допущения!$B$13) | J16: =F16-G16-H16-I16 | K16: =K15+J16 | L16: =IF(K16>=0,A16,"") | M16: =IF(J16>0,A16,"")
A17: 13 | B17: =IF(A17<Допущения!$B$16,0,MIN(Допущения!$B$19,ROUND(Допущения!$B$17*(1+Допущения!$B$18)^(A17-Допущения!$B$16),0))) | C17: =ROUND(D16*Допущения!$B$14,0) | D17: =D16+B17-C17 | E17: =D17*Допущения!$B$11 | F17: =D17*Допущения!$B$10 | G17: =(D17+E17)*Допущения!$B$21 | H17: =Расходы!$C$24 | I17: =F17*(Допущения!$B$12+Допущения!$B$13) | J17: =F17-G17-H17-I17 | K17: =K16+J17 | L17: =IF(K17>=0,A17,"") | M17: =IF(J17>0,A17,"")
... A28: 24 | B28: =IF(A28<Допущения!$B$16,0,MIN(Допущения!$B$19,ROUND(Допущения!$B$17*(1+Допущения!$B$18)^(A28-Допущения!$B$16),0))) | C28: =ROUND(D27*Допущения!$B$14,0) | D28: =D27+B28-C28 | E28: =D28*Допущения!$B$11 | F28: =D28*Допущения!$B$10 | G28: =(D28+E28)*Допущения!$B$21 | H28: =Расходы!$C$24 | I28: =F28*(Допущения!$B$12+Допущения!$B$13) | J28: =F28-G28-H28-I28 | K28: =K27+J28 | L28: =IF(K28>=0,A28,"") | M28: =IF(J28>0,A28,"")
A30: Итого за 24 месяца | F30: =SUM(F5:F28) | G30: =SUM(G5:G28) | H30: =SUM(H5:H28) | I30: =SUM(I5:I28) | J30: =SUM(J5:J28)
A31: Разовые расходы на запуск (учтены в накопленном итоге с 1-го месяца) | J31: =Расходы!C11

Sheet Безубыточность
A1: Точка безубыточности: сколько платных клиентов покрывают постоянные расходы
A2: Маржа с одного платного клиента = цена × (1 − эквайринг − налог) − переменные расходы на него и на его бесплатных пользователей. Клиентов = постоянные расходы ÷ маржа.
A4: Тариф / смесь | B4: Цена, ₽/мес | C4: Маржа с клиента, ₽/мес | D4: Клиентов для безубыточности (мин.) | E4: Клиентов для безубыточности (реал.)
A5: Только «Базовый» | B5: =Допущения!B6 | C5: =B5*(1-Допущения!$B$12-Допущения!$B$13)-Допущения!$B$21*(1+Допущения!$B$11) | D5: =IF(C5>0,ROUNDUP(Расходы!$B$24/C5,0),"не окупается") | E5: =IF(C5>0,ROUNDUP(Расходы!$C$24/C5,0),"не окупается")
A6: Только «Профессиональный» | B6: =Допущения!B7 | C6: =B6*(1-Допущения!$B$12-Допущения!$B$13)-Допущения!$B$21*(1+Допущения!$B$11) | D6: =IF(C6>0,ROUNDUP(Расходы!$B$24/C6,0),"не окупается") | E6: =IF(C6>0,ROUNDUP(Расходы!$C$24/C6,0),"не окупается")
A7: Смесь тарифов (по доле из допущений) | B7: =Допущения!B10 | C7: =B7*(1-Допущения!$B$12-Допущения!$B$13)-Допущения!$B$21*(1+Допущения!$B$11) | D7: =IF(C7>0,ROUNDUP(Расходы!$B$24/C7,0),"не окупается") | E7: =IF(C7>0,ROUNDUP(Расходы!$C$24/C7,0),"не окупается")
A9: Постоянные расходы в месяц, ₽ | D9: =Расходы!B24 | E9: =Расходы!C24
A10: Для окупаемости разовых расходов нужна ещё накопленная прибыль: см. листы «Прогноз».
